{
  "db_name": "PostgreSQL",
  "query": "SELECT * FROM clients_x509",
  "describe": {
    "columns": [
      {
        "ordinal": 0,
        "name": "id",
        "type_info": "Uuid"
      },
      {
        "ordinal": 1,
        "name": "name",
        "type_info": "Varchar"
      },
      {
        "ordinal": 2,
        "name": "expires",
        "type_info": "Timestamptz"
      },
      {
        "ordinal": 3,
        "name": "enabled",
        "type_info": "Bool"
      },
      {
        "ordinal": 4,
        "name": "group_id",
        "type_info": "Uuid"
      },
      {
        "ordinal": 5,
        "name": "api_key",
        "type_info": "Bytea"
      },
      {
        "ordinal": 6,
        "name": "enc_key_id",
        "type_info": "Uuid"
      },
      {
        "ordinal": 7,
        "name": "key_alg",
        "type_info": "Varchar"
      },
      {
        "ordinal": 8,
        "name": "common_name",
        "type_info": "Varchar"
      },
      {
        "ordinal": 9,
        "name": "country",
        "type_info": "Varchar"
      },
      {
        "ordinal": 10,
        "name": "locality",
        "type_info": "Varchar"
      },
      {
        "ordinal": 11,
        "name": "organizational_unit",
        "type_info": "Varchar"
      },
      {
        "ordinal": 12,
        "name": "organization",
        "type_info": "Varchar"
      },
      {
        "ordinal": 13,
        "name": "state_or_province",
        "type_info": "Varchar"
      },
      {
        "ordinal": 14,
        "name": "alt_names_dns",
        "type_info": "Varchar"
      },
      {
        "ordinal": 15,
        "name": "alt_names_ip",
        "type_info": "Varchar"
      },
      {
        "ordinal": 16,
        "name": "key_usage",
        "type_info": "Bytea"
      },
      {
        "ordinal": 17,
        "name": "key_usage_ext",
        "type_info": "Bytea"
      },
      {
        "ordinal": 18,
        "name": "valid_hours",
        "type_info": "Int4"
      },
      {
        "ordinal": 19,
        "name": "email",
        "type_info": "Varchar"
      },
      {
        "ordinal": 20,
        "name": "latest_cert",
        "type_info": "Int4"
      }
    ],
    "parameters": {
      "Left": []
    },
    "nullable": [
      false,
      false,
      true,
      false,
      false,
      false,
      false,
      false,
      false,
      true,
      true,
      true,
      true,
      true,
      false,
      false,
      true,
      true,
      false,
      false,
      true
    ]
  },
  "hash": "c61eeb0e493801e585583a87fd67877e2629df7e3c23bfd44c6a1fa0a1399259"
}
